{
 "name": "Gaber_Rollobad",
 "display_name": "Gaber Rollobad",
 "side_bars": [
  {
   "name": "Physical description",
   "attributes": [
    {
     "name": "Species",
     "values": [
      "Sullustan"
     ]
    },
    {
     "name": "Gender",
     "values": [
      "Male"
     ]
    }
   ]
  }
 ],
 "content": "Gaber Rollobad was a Sullustan male smuggler who owned the YT-1210 light freighter Boolarg.\nOn a gun-run, Rollobad was shot down over Corellia by the Star Destroyer Shrike and crashed his escape pod near the Boolarg. He attempted to enlist the aid of freelancers to recover the weapons shipment, which was hidden in a compartment onboard his vessel, but was caught by Imperial officials in the process.",
 "base_url": "https://starwars.fandom.com",
 "crosslinks": [
  "/wiki/Star_Wars_Legends",
  "/wiki/Sullustan/Legends",
  "/wiki/Gender/Legends",
  "/wiki/Smuggler/Legends",
  "/wiki/YT-1210_light_freighter/Legends",
  "/wiki/Boolarg",
  "/wiki/Corellia/Legends",
  "/wiki/Star_Destroyer/Legends",
  "/wiki/Shrike_(Star_Destroyer)",
  "/wiki/Escape_pod/Legends",
  "/wiki/Coruscant_and_the_Core_Worlds"
 ]
}