{
 "name": "Gorneesh",
 "side_bars": [
  {
   "name": "Biographical information",
   "attributes": [
    {
     "name": "Homeworld",
     "values": [
      "Endor"
     ]
    }
   ]
  },
  {
   "name": "Physical description",
   "attributes": [
    {
     "name": "Species",
     "values": [
      "Dulok"
     ]
    },
    {
     "name": "Gender",
     "values": [
      "Male"
     ]
    },
    {
     "name": "Hair color",
     "values": [
      "Green"
     ]
    },
    {
     "name": "Eye color",
     "values": [
      "Red"
     ]
    },
    {
     "name": "Skin color",
     "values": [
      "Brown"
     ]
    }
   ]
  },
  {
   "name": "Chronological and political information",
   "attributes": [
    {
     "name": "Affiliation(s)",
     "values": [
      "DuloksGorneesh's tribe",
      "Gorneesh's tribe",
      "Morag"
     ]
    }
   ]
  }
 ],
 "content": "Gorneesh was the king of a tribe of Duloks on Endor during the time of the Galactic Civil War. His wife was named Urgah, and he had three children, including Prince Boogutt. Gorneesh and his Duloks were the sworn enemies of the Ewoks of Bright Tree Village.\nKing Gorneesh appeared in the animated television series Ewoks, where he was voiced by Dan Hennessey in the first season.",
 "base_url": "https://starwars.fandom.com/",
 "crosslinks": [
  "/wiki/Star_Wars_Legends",
  "/wiki/Endor/Legends",
  "/wiki/Dulok/Legends",
  "/wiki/Gender/Legends",
  "/wiki/Gorneesh%27s_tribe",
  "/wiki/Morag",
  "/wiki/King/Legends",
  "/wiki/Galactic_Civil_War/Legends",
  "/wiki/Urgah",
  "/wiki/Prince/Legends",
  "/wiki/Boogutt",
  "/wiki/Ewok/Legends",
  "/wiki/Bright_Tree_Village/Legends",
  "/wiki/Wookieepedia:Stub",
  "/wiki/Special:EditPage/Gorneesh",
  "/wiki/Starlog_(magazine)#Starlog_Yearbook_3",
  "/wiki/Ewoks_(TV_series)",
  "/wiki/Dan_Hennessey",
  "/wiki/Ewoks:_Season_One",
  "/wiki/Ewoks_10",
  "/wiki/Ewoks_13",
  "/wiki/The_Haunted_Village",
  "/wiki/Rampage_of_the_Phlogs",
  "/wiki/The_Travelling_Jindas",
  "/wiki/The_Tree_of_Light",
  "/wiki/Wicket%27s_Wagon",
  "/wiki/Blue_Harvest",
  "/wiki/Asha_(episode)",
  "/wiki/A_Gift_for_Shodu",
  "/wiki/Night_of_the_Stranger",
  "/wiki/Prow_Beaten",
  "/wiki/Star_Wars:_Ewoks_(toy_line)",
  "/wiki/Droids%5CEwoks",
  "/wiki/A_Guide_to_the_Star_Wars_Universe,_Second_Edition,_Revised_and_Expanded",
  "/wiki/The_Essential_Guide_to_Characters",
  "/wiki/Star_Wars_Encyclopedia",
  "/wiki/Star_Wars:_The_Action_Figure_Archive",
  "/wiki/The_Complete_Star_Wars_Encyclopedia",
  "/wiki/StarWars.com"
 ]
}