{
 "name": "Gremac",
 "display_name": "Gremac",
 "side_bars": [
  {
   "name": "Biographical information",
   "attributes": [
    {
     "name": "Homeworld",
     "values": [
      "Lenahra"
     ]
    }
   ]
  },
  {
   "name": "Physical description",
   "attributes": [
    {
     "name": "Species",
     "values": [
      "Iktotchi"
     ]
    },
    {
     "name": "Gender",
     "values": [
      "Male"
     ]
    }
   ]
  },
  {
   "name": "Chronological and political information",
   "attributes": [
    {
     "name": "Affiliation(s)",
     "values": [
      "Lenahrans"
     ]
    }
   ]
  }
 ],
 "content": "Gremac was an Iktotchi boy from the planet Lenahra. By 41 BBY, he was a young and cautious but cheerful child.\n]]",
 "base_url": "https://starwars.fandom.com",
 "crosslinks": [
  "/wiki/Canon",
  "/wiki/Lenahra",
  "/wiki/Iktotchi",
  "/wiki/Gender",
  "/wiki/Lenahran",
  "/wiki/Planet",
  "/wiki/41_BBY",
  "/wiki/Youngling",
  "/wiki/Wookieepedia:Stub",
  "/wiki/Special:EditPage/Gremac",
  "/wiki/Padawan_(novel)",
  "/wiki/Padawan_(audiobook)",
  "/wiki/Obi-Wan_Kenobi",
  "/wiki/Standard_year",
  "/wiki/The_Topps_Company,_Inc.",
  "/wiki/Star_Wars:_Card_Trader",
  "/wiki/Reproduction",
  "/wiki/57_BBY"
 ]
}