{
 "name": "Kasdakh Bhul",
 "side_bars": [
  {
   "name": "Physical description",
   "attributes": [
    {
     "name": "Species",
     "values": [
      "Yuuzhan Vong"
     ]
    },
    {
     "name": "Gender",
     "values": [
      "Male"
     ]
    }
   ]
  },
  {
   "name": "Chronological and political information",
   "attributes": [
    {
     "name": "Caste",
     "values": [
      "Warrior caste"
     ]
    }
   ]
  }
 ],
 "content": "Kasdakh Bhul was a member of the Yuuzhan Vong Warrior caste and Czulkang Lah's second-in-command aboard his worldship at the Battle of Borleias.\nKnown for his courage by none other than Czulkang Lah himself, Kasdakh was a gruff and wary commander.",
 "base_url": "https://starwars.fandom.com/",
 "crosslinks": [
  "/wiki/Star_Wars_Legends",
  "/wiki/Yuuzhan_Vong",
  "/wiki/Gender/Legends",
  "/wiki/Warrior_caste",
  "/wiki/Czulkang_Lah",
  "/wiki/Koros-Strohna",
  "/wiki/Battle_of_Borleias_(Yuuzhan_Vong_War;_Second)",
  "/wiki/Wookieepedia:Sourcing",
  "/wiki/Wookieepedia:Stub",
  "/wiki/Special:EditPage/Kasdakh_Bhul",
  "/wiki/The_New_Jedi_Order:_Enemy_Lines_II:_Rebel_Stand",
  "/wiki/The_Complete_Star_Wars_Encyclopedia"
 ]
}