{
 "name": "Lorn Kabul",
 "side_bars": [
  {
   "name": "Biographical information",
   "attributes": [
    {
     "name": "Homeworld",
     "values": [
      "Otunia"
     ]
    },
    {
     "name": "Died",
     "values": [
      "4 ABY",
      "Otunia"
     ]
    }
   ]
  },
  {
   "name": "Physical description",
   "attributes": [
    {
     "name": "Species",
     "values": [
      "Human"
     ]
    },
    {
     "name": "Gender",
     "values": [
      "Male"
     ]
    },
    {
     "name": "Hair color",
     "values": [
      "Brown"
     ]
    },
    {
     "name": "Skin color",
     "values": [
      "Fair"
     ]
    }
   ]
  },
  {
   "name": "Chronological and political information",
   "attributes": [
    {
     "name": "Affiliation(s)",
     "values": [
      "Kabul Industries"
     ]
    }
   ]
  }
 ],
 "content": "Lorn Kabul, addressed as \"Lord Kabul\" and \"Master Kabul\", was the owner of a mining operation on Otunia and the father of Arista Kabul.\nA loving father, Lorn nevertheless thought Arista was too irresponsible and made her wear a tracking device on her ankle at all times.\nHe was killed by his brother Seth Kabul who, scheming with the Imperial Moff Harsh wanted to take over the mining operation. As Lorn lay dying, he asked the unusually noble Gamorrean, Grissom, to protect Arista and help her make it off-planet.",
 "base_url": "https://starwars.fandom.com/",
 "crosslinks": [
  "/wiki/Star_Wars_Legends",
  "/wiki/Otunia",
  "/wiki/4_ABY/Legends",
  "/wiki/Human/Legends",
  "/wiki/Gender/Legends",
  "/wiki/Color/Legends",
  "/wiki/Kabul_Industries",
  "/wiki/Arista_Kabul",
  "/wiki/Homing_beacon/Legends",
  "/wiki/Seth_Kabul",
  "/wiki/Galactic_Empire/Legends",
  "/wiki/Moff/Legends",
  "/wiki/Harsh",
  "/wiki/Gamorrean/Legends",
  "/wiki/Grissom_(Gamorrean)",
  "/wiki/Three_Against_the_Galaxy",
  "/wiki/Star_Wars_Tales_3"
 ]
}