{
 "name": "Siron_Vurn%27ke",
 "display_name": "Siron Vurn'ke",
 "side_bars": [
  {
   "name": "Biographical information",
   "attributes": [
    {
     "name": "Died",
     "values": [
      "1 ABY",
      "Tatooine"
     ]
    }
   ]
  },
  {
   "name": "Physical description",
   "attributes": [
    {
     "name": "Species",
     "values": [
      "Weequay"
     ]
    },
    {
     "name": "Gender",
     "values": [
      "Male"
     ]
    },
    {
     "name": "Hair color",
     "values": [
      "Brown"
     ]
    },
    {
     "name": "Eye color",
     "values": [
      "Gray"
     ]
    },
    {
     "name": "Skin color",
     "values": [
      "Brown"
     ]
    }
   ]
  },
  {
   "name": "Chronological and political information",
   "attributes": [
    {
     "name": "Affiliation(s)",
     "values": [
      "Jabba Desilijic Tiure's criminal empire"
     ]
    }
   ]
  }
 ],
 "content": "Siron Vurn'ke was a male Weequay criminal who lived on Tatooine during the time of the Galactic Civil War. After the Battle of Yavin, he was the captain of a group of Weequay thugs working for the Hutt crime lord Jabba Desilijic Tiure. In 1 ABY, Jabba tasked Vurn'ke's hit squad with eliminating a skiled spacer loyal to Lady Valarian, the leader of the Valarian Syndicate and main rival of Jabba. However, Lady Valarian discovered the situation and warned her henchman. The spacer then found and attacked Vurn'ke and four Weequay zealots near Mos Eisley. Siron Vurn'ke was killed in the firefight.\nSiron Vurn'ke was a non-player character in the 2003 video game Star Wars Galaxies, a massively multiplayer online roleplaying game developed by Sony Online Entertainment and published by LucasArts, prior to its closure on December 15, 2011. Siron Vurn'ke was present in the original release of the game, being part of Lady Valarian's Quest Series.\nWith the release of the \"Publish 23\" on August 31, 2005, Lady Valarian's Quest Series was deactivated and Siron Vurn'ke was consequently removed from the game.",
 "base_url": "https://starwars.fandom.com",
 "crosslinks": [
  "/wiki/Star_Wars_Legends",
  "/wiki/1_ABY/Legends",
  "/wiki/Tatooine/Legends",
  "/wiki/Weequay/Legends",
  "/wiki/Gender/Legends",
  "/wiki/Color/Legends",
  "/wiki/Jabba_Desilijic_Tiure%27s_criminal_empire",
  "/wiki/Lord/Legends",
  "/wiki/Valarian/Legends",
  "/wiki/Time/Legends",
  "/wiki/Galactic_Civil_War/Legends",
  "/wiki/Battle_of_Yavin/Legends",
  "/wiki/Captain/Legends",
  "/wiki/Hutt/Legends",
  "/wiki/Crime_lord/Legends",
  "/wiki/Jabba_Desilijic_Tiure/Legends",
  "/wiki/Valarian_Syndicate",
  "/wiki/Mos_Eisley/Legends",
  "/wiki/2003",
  "/wiki/Video_game",
  "/wiki/Star_Wars_Galaxies",
  "/wiki/Sony",
  "/wiki/LucasArts",
  "/wiki/December_15",
  "/wiki/2011",
  "/wiki/August_31",
  "/wiki/2005",
  "/wiki/Opening_crawl",
  "/wiki/Star_Wars:_Episode_IV_A_New_Hope",
  "/wiki/Ruwan_Tokai",
  "/wiki/DS-1_Orbital_Battle_Station/Legends",
  "/wiki/The_Essential_Reader%27s_Companion",
  "/wiki/Star_Wars_Galaxies:_Rage_of_the_Wookiees",
  "/wiki/Blockade_of_Kashyyyk_(1_ABY)",
  "/wiki/The_Star_Wars_Holiday_Special",
  "/wiki/The_Nightsister%27s_Revenge",
  "/wiki/Star_Wars_Galaxies_Trading_Card_Game",
  "/wiki/Battle_of_Hoth/Legends",
  "/wiki/3_ABY/Legends",
  "/wiki/Strongholds_of_Resistance"
 ]
}