{
 "name": "TK-127",
 "display_name": "TK-127",
 "side_bars": [
  {
   "name": "Physical description",
   "attributes": [
    {
     "name": "Species",
     "values": [
      "Human"
     ]
    },
    {
     "name": "Gender",
     "values": [
      "Male"
     ]
    }
   ]
  },
  {
   "name": "Chronological and political information",
   "attributes": [
    {
     "name": "Affiliation(s)",
     "values": [
      "Galactic Empire",
      "Stormtrooper Corps",
      "Stormtrooper Corps"
     ]
    }
   ]
  }
 ],
 "content": "TK-127 was a human male stormtrooper who served the Galactic Empire on Endor. At some point, he was captured and tied up by Ewoks of the Bright Tree tribe, and became worried when Chief Chirpa reached for Yub Nub Yuzzum Marinade.\nTK-127 is featured in a non-canonical section of Launchpad in Star Wars Insider 210 that was written by Jamie Cosley.",
 "base_url": "https://starwars.fandom.com",
 "crosslinks": [
  "/wiki/Canon",
  "/wiki/Lucasfilm_Ltd.",
  "/wiki/Human",
  "/wiki/Gender",
  "/wiki/Galactic_Empire",
  "/wiki/Stormtrooper_Corps",
  "/wiki/Stormtrooper",
  "/wiki/Endor",
  "/wiki/Ewok",
  "/wiki/Bright_Tree_tribe",
  "/wiki/Chief",
  "/wiki/Chirpa",
  "/wiki/Yub_Nub_Yuzzum_Marinade",
  "/wiki/Launchpad",
  "/wiki/Star_Wars_Insider_210",
  "/wiki/Jamie_Cosley",
  "/wiki/Star_Wars_Insider",
  "/wiki/2016",
  "/wiki/Star_Wars_Character_Encyclopedia:_Updated_and_Expanded"
 ]
}