{
 "name": "Unidentified_Spiderclan_stalker",
 "display_name": "Unidentified Spiderclan stalker",
 "side_bars": [
  {
   "name": "Biographical information",
   "attributes": [
    {
     "name": "Homeworld",
     "values": [
      "Dathomir"
     ]
    }
   ]
  },
  {
   "name": "Physical description",
   "attributes": [
    {
     "name": "Species",
     "values": [
      "Dathomirian"
     ]
    },
    {
     "name": "Gender",
     "values": [
      "Female"
     ]
    },
    {
     "name": "Skin color",
     "values": [
      "Dark"
     ]
    }
   ]
  },
  {
   "name": "Chronological and political information",
   "attributes": [
    {
     "name": "Clan(s)",
     "values": [
      "Spiderclan"
     ]
    },
    {
     "name": "Affiliation(s)",
     "values": [
      "Nightsisters"
     ]
    }
   ]
  }
 ],
 "content": "An female individual was a member of the Spiderclan, one of the clans on Dathomir that made up the Nightsisters, during the Galactic Civil War. She had dark skin with white tattoos, black eyes, and black hair. She wore brown robes and wielded two swords.\nThe Spiderclan stalker was pictured on the card \"Spiderclan Stalker\" from the Nightsister's Revenge expansion set of the Star Wars Galaxies Trading Card Game. The set was released on December 15, 2009. The Spiderclan Stalker was drawn by Ben Wootten.",
 "base_url": "https://starwars.fandom.com",
 "crosslinks": [
  "/wiki/Star_Wars_Legends",
  "/wiki/Dathomir/Legends",
  "/wiki/Dathomirian/Legends",
  "/wiki/Gender/Legends",
  "/wiki/Color/Legends",
  "/wiki/Spiderclan/Legends",
  "/wiki/Nightsisters/Legends",
  "/wiki/The_Nightsister%27s_Revenge",
  "/wiki/Galactic_Civil_War/Legends",
  "/wiki/Tattoo/Legends",
  "/wiki/Eye/Legends",
  "/wiki/Robe/Legends",
  "/wiki/Sword/Legends",
  "/wiki/Star_Wars_Galaxies_Trading_Card_Game",
  "/wiki/December_15",
  "/wiki/2009",
  "/wiki/Ben_Wootten",
  "/wiki/Template:SWGTCG",
  "/wiki/Star_Wars_Galaxies"
 ]
}