{
 "name": "Unidentified_Arratu",
 "display_name": "Unidentified Arratu",
 "side_bars": [
  {
   "name": "Biographical information",
   "attributes": [
    {
     "name": "Homeworld",
     "values": [
      "Parnassos"
     ]
    },
    {
     "name": "Died",
     "values": [
      "24 ABY",
      "Parnassos"
     ]
    }
   ]
  },
  {
   "name": "Physical description",
   "attributes": [
    {
     "name": "Species",
     "values": [
      "Human"
     ]
    },
    {
     "name": "Gender",
     "values": [
      "Male"
     ]
    },
    {
     "name": "Skin color",
     "values": [
      "White"
     ]
    }
   ]
  },
  {
   "name": "Chronological and political information",
   "attributes": [
    {
     "name": "Affiliation(s)",
     "values": [
      "Arratu Station"
     ]
    }
   ]
  }
 ],
 "content": "An Arratu captured Brendol Hux, Phasma, and his company when they were in Arratu Station on the planet Parnassos. He intended for them be warriors in his gladiatorial games, which would entertain the people of the nearby city. After the soldiers defeated and killed Wranderous, the champion of the games, Phasma jumped to the Arratu's box and killed him.",
 "base_url": "https://starwars.fandom.com",
 "crosslinks": [
  "/wiki/Canon",
  "/wiki/Wookieepedia:Layout_Guide",
  "/wiki/Wookieepedia:Manual_of_Style",
  "/wiki/Parnassos",
  "/wiki/24_ABY",
  "/wiki/Human",
  "/wiki/Gender",
  "/wiki/Arratu_Station",
  "/wiki/Arratu",
  "/wiki/Brendol_Hux",
  "/wiki/Phasma",
  "/wiki/Wranderous",
  "/wiki/Wookieepedia:Stub",
  "/wiki/Special:EditPage/Unidentified_Arratu",
  "/wiki/Phasma_(novel)",
  "/wiki/Phasma_(audiobook)",
  "/wiki/Standard_week",
  "/wiki/Galaxy%27s_Edge:_Black_Spire",
  "/wiki/Star_Wars:_Episode_VII_The_Force_Awakens",
  "/wiki/34_ABY",
  "/wiki/Star_Wars:_Galactic_Atlas",
  "/wiki/Star_Wars_Insider",
  "/wiki/Resistance_Revisited",
  "/wiki/Star_Wars_Insider_190",
  "/wiki/Star_Wars_Resistance_Season_One",
  "/wiki/Standard_year",
  "/wiki/Battle_of_Endor",
  "/wiki/Star_Wars:_The_Rise_of_Skywalker:_The_Visual_Dictionary",
  "/wiki/Star_Wars_Resistance",
  "/wiki/%27ABY-BBY%27_dating_system",
  "/wiki/Death"
 ]
}