{
 "name": "Xodlak%27oo%27nifis",
 "display_name": "Xodlak'oo'nifis",
 "side_bars": [
  {
   "name": "Physical description",
   "attributes": [
    {
     "name": "Species",
     "values": [
      "Chiss"
     ]
    },
    {
     "name": "Gender",
     "values": [
      "Female"
     ]
    }
   ]
  },
  {
   "name": "Chronological and political information",
   "attributes": [
    {
     "name": "Affiliation(s)",
     "values": [
      "Chiss Ascendancy",
      "Xodlak family",
      "Xodlak family"
     ]
    }
   ]
  }
 ],
 "content": "Xodlak'oo'nifis, core name Lakooni, was a Chiss female who was the Patriel of the planet Celwis, a stronghold of the Xodlak family. Lakooni held the rank of blood within the Xodlak family.",
 "base_url": "https://starwars.fandom.com",
 "crosslinks": [
  "/wiki/Canon",
  "/wiki/Chiss",
  "/wiki/Gender",
  "/wiki/Chiss_Ascendancy",
  "/wiki/Xodlak_family",
  "/wiki/Core_name",
  "/wiki/Patriel",
  "/wiki/Planet",
  "/wiki/Celwis",
  "/wiki/Blood_(rank)",
  "/wiki/Chiss_family",
  "/wiki/Wookieepedia:Stub",
  "/wiki/Special:EditPage/Xodlak%27oo%27nifis",
  "/wiki/Thrawn_Ascendancy:_Greater_Good",
  "/wiki/Thrawn_Ascendancy:_Greater_Good_(audiobook)",
  "/wiki/Thrawn_Ascendancy:_Lesser_Evil",
  "/wiki/Thrawn_Ascendancy:_Lesser_Evil_(audiobook)"
 ]
}